[
  {
    "name": "Linked In",
    "desc": "It's my linked in profile (Testing)",
    "image": "linkedin",
    "category": "category",
    "links": {
      "view": "https://www.linkedin.com/in/srivasanthvutukuri/",
      "code": "https://www.linkedin.com/in/srivasanthvutukuri/"
    }
  },

  {
     "name": "Typing Kudos",
     "desc": "Python Based Typing Test",
     "image": "typing kudos",
     "category": "python",
     "links": {
     "view": "https://www.linkedin.com/in/srivasanthvutukuri/",
     "code": "https://www.linkedin.com/in/srivasanthvutukuri/"
    }
  },

  {
    "name": "Vagah's book hub",
    "desc": "HTML,CSS,JS based website",
    "image": "book hub",
    "category": "website",
    "links": {
      "view": "https://www.linkedin.com/in/srivasanthvutukuri/",
      "code": "https://www.linkedin.com/in/srivasanthvutukuri/"
    }
  }

]
